CHANGES.txt
LICENSE.txt
MANIFEST.in
README.md
pyproject.toml
setup.cfg
setup.py
tox.ini
src/pyramid_forksafe/__init__.py
src/pyramid_forksafe/events.py
src/pyramid_forksafe/interfaces.py
src/pyramid_forksafe/py.typed
src/pyramid_forksafe.egg-info/PKG-INFO
src/pyramid_forksafe.egg-info/SOURCES.txt
src/pyramid_forksafe.egg-info/dependency_links.txt
src/pyramid_forksafe.egg-info/not-zip-safe
src/pyramid_forksafe.egg-info/requires.txt
src/pyramid_forksafe.egg-info/top_level.txt
src/pyramid_forksafe/containers/__init__.py
src/pyramid_forksafe/containers/gunicorn.py
src/pyramid_forksafe/containers/uwsgi.py
src/pyramid_forksafe/debugtoolbar/__init__.py
src/pyramid_forksafe/debugtoolbar/panels/__init__.py
src/pyramid_forksafe/debugtoolbar/panels/forksafe.py
src/pyramid_forksafe/debugtoolbar/panels/templates/forksafe.dbtmako
tests/__init__.py
tests/test_config.py