Metadata-Version: 2.1
Name: pyramid-forksafe
Version: 0.2.0
Summary: Standardizes server `fork` events into Pyrmamid events
Home-page: https://github.com/jvanasco/pyramid_forksafe
Author: Jonathan Vanasco
Author-email: jonathan@findmeon.com
License: MIT
Keywords: web pyramid fork uwsgi nginx
Classifier: Intended Audience :: Developers
Classifier: Framework :: Pyramid
Classifier: Programming Language :: Python
Classifier: Programming Language :: Python :: 3
Classifier: Programming Language :: Python :: 3.6
Classifier: Programming Language :: Python :: 3.7
Classifier: Programming Language :: Python :: 3.8
Classifier: Programming Language :: Python :: 3.9
Classifier: Programming Language :: Python :: 3.10
Classifier: Programming Language :: Python :: 3.11
Classifier: License :: OSI Approved :: MIT License
Provides-Extra: testing
License-File: LICENSE.txt
